pcl_pangu/__init__.py
pcl_pangu/context/__init__.py
pcl_pangu/context/check_context.py
pcl_pangu/context/context.py
pcl_pangu/dataset/__init__.py
pcl_pangu/dataset/pre_process_chinese.py
pcl_pangu/dataset/preprocess_data_pangu.py
pcl_pangu/dataset/txt2bin.py
pcl_pangu/dataset/txt2mindrecord.py
pcl_pangu/model/__init__.py
pcl_pangu/model/launcher_torch.py
pcl_pangu/model/alpha/__init__.py
pcl_pangu/model/alpha/alpha.py
pcl_pangu/model/alpha/config_alpha.py
pcl_pangu/model/evolution/__init__.py
pcl_pangu/model/evolution/config_evolution.py
pcl_pangu/model/evolution/evolution.py
pcl_pangu/model/mPangu/__init__.py
pcl_pangu/model/mPangu/config_mPangu.py
pcl_pangu/model/mPangu/mPangu.py
pcl_pangu/model/panguAlpha_mindspore/__init__.py
pcl_pangu/model/panguAlpha_mindspore/inference_alpha_ms13.py
pcl_pangu/model/panguAlpha_mindspore/train_alpha_ms13.py
pcl_pangu/model/panguAlpha_mindspore/src/__init__.py
pcl_pangu/model/panguAlpha_mindspore/src/dataset.py
pcl_pangu/model/panguAlpha_mindspore/src/generate.py
pcl_pangu/model/panguAlpha_mindspore/src/pangu_alpha.py
pcl_pangu/model/panguAlpha_mindspore/src/pangu_alpha_config.py
pcl_pangu/model/panguAlpha_mindspore/src/pangu_alpha_wrapcell.py
pcl_pangu/model/panguAlpha_mindspore/src/preprocess.py
pcl_pangu/model/panguAlpha_mindspore/src/serialization.py
pcl_pangu/model/panguAlpha_mindspore/src/tokenization_jieba.py
pcl_pangu/model/panguAlpha_mindspore/src/utils_pangu.py
pcl_pangu/model/panguAlpha_pytorch/3-minus-inference-en.md
pcl_pangu/model/panguAlpha_pytorch/3-minus-inference.md
pcl_pangu/model/panguAlpha_pytorch/LICENSE
pcl_pangu/model/panguAlpha_pytorch/MANIFEST.in
pcl_pangu/model/panguAlpha_pytorch/README-en.md
pcl_pangu/model/panguAlpha_pytorch/README.md
pcl_pangu/model/panguAlpha_pytorch/README_mgt.md
pcl_pangu/model/panguAlpha_pytorch/__init__.py
pcl_pangu/model/panguAlpha_pytorch/mergeMpCkpt.py
pcl_pangu/model/panguAlpha_pytorch/pretrain_bert.py
pcl_pangu/model/panguAlpha_pytorch/pretrain_evolution.py
pcl_pangu-1.2.6.2.dist-info/LICENSE
pcl_pangu-1.2.6.2.dist-info/METADATA
pcl_pangu-1.2.6.2.dist-info/WHEEL
pcl_pangu-1.2.6.2.dist-info/top_level.txt
pcl_pangu-1.2.6.2.dist-info/RECORD
