Metadata-Version: 2.1
Name: pcl-pangu
Version: 1.2.6.2
Summary: pcl_pangu
Home-page: https://openi.pcl.ac.cn/PCL-Platform.Intelligence/pcl_pangu
Author: 2022 PCL
Author-email: pcl.openi@pcl.ac.cn
License: UNKNOWN
Platform: UNKNOWN
Requires-Python: >=3.6.2,<4.0.0
License-File: LICENSE
Requires-Dist: numpy (<2.0.0,>=1.17.5)
Requires-Dist: sentencepiece (>=0.1.0)
Requires-Dist: jieba (>=0.32.0)
Requires-Dist: loguru (>=0.3.0)
Requires-Dist: dataclasses (==0.6) ; python_version < "3.7"
